<?xml version = "1.0" encoding = "utf-8" ?>
<root>
<item>
	<name>brandbrandbrandbran</name>
	<short_description></short_description>
	<link>https://salesmanago.store/product/water-repellent-quilted-jacket/</link>
	<price>89</price>
	<currency>USD</currency>
	<image_url>https://salesmanago.store/wp-content/uploads/2021/09/Water-repellent-quilted-jacket.png</image_url>
	<image_url_1>https://salesmanago.store/wp-content/uploads/2021/09/Water-repellent-quilted-jacket-1.png</image_url_1>
	<sku>299</sku>
	<stock_quantity>12</stock_quantity>
	<categories>Jackets &amp; Coats, Men</categories>
	<tags>Jackets and Coats, Men</tags>
	<total_sales>0</total_sales>
</item>
<item>
	<name><![CDATA[Pockets textured overshirt]]></name>
	<short_description></short_description>
	<link>https://salesmanago.store/product/pockets-textured-overshirt-2/</link>
	<price>49</price>
	<currency>USD</currency>
	<image_url>https://salesmanago.store/wp-content/uploads/2021/09/Pockets-textured-overshirt-2.png</image_url>
	<image_url_1>https://salesmanago.store/wp-content/uploads/2021/09/Pockets-textured-overshirt.png</image_url_1>
	<sku>103</sku>
	<stock_quantity>11</stock_quantity>
	<categories>Men, Overshirts</categories>
	<tags>Men, Overshirts</tags>
	<total_sales>0</total_sales>
</item>
<item>
	<name><![CDATA[Pockets textured overshirt]]></name>
	<short_description></short_description>
	<link>https://salesmanago.store/product/pockets-textured-overshirt/</link>
	<price>49</price>
	<currency>USD</currency>
	<image_url>https://salesmanago.store/wp-content/uploads/2021/09/Pocket-denim-overshirt-2.png</image_url>
	<image_url_1>https://salesmanago.store/wp-content/uploads/2021/09/Pocket-denim-overshirt.png</image_url_1>
	<sku>104</sku>
	<stock_quantity>18</stock_quantity>
	<categories>Men, Overshirts</categories>
	<tags>Men, Overshirts</tags>
	<total_sales>0</total_sales>
</item>
<item>
	<name><![CDATA[Pocket denim overshirt]]></name>
	<short_description></short_description>
	<link>https://salesmanago.store/product/pocket-denim-overshirt/</link>
	<price>35</price>
	<currency>USD</currency>
	<image_url>https://salesmanago.store/wp-content/uploads/2021/09/Pocket-denim-overshirt-6.png</image_url>
	<image_url_1>https://salesmanago.store/wp-content/uploads/2021/09/Pocket-denim-overshirt-7.png</image_url_1>
	<sku>105</sku>
	<stock_quantity>13</stock_quantity>
	<categories>Men, Overshirts</categories>
	<tags>Men, Overshirts</tags>
	<total_sales>0</total_sales>
</item>
<item>
	<name><![CDATA[Sustainable cotton basic T-shirt]]></name>
	<short_description></short_description>
	<link>https://salesmanago.store/product/sustainable-cotton-basic-t-shirt-7/</link>
	<price>12</price>
	<currency>USD</currency>
	<image_url>https://salesmanago.store/wp-content/uploads/2021/09/Sustainable-cotton-basic-T-shirt-13.png</image_url>
	<image_url_1>https://salesmanago.store/wp-content/uploads/2021/09/Sustainable-cotton-basic-T-shirt-14.png</image_url_1>
	<sku>106</sku>
	<stock_quantity>18</stock_quantity>
	<categories>Men, T-shirts</categories>
	<tags>Men, T-shirts</tags>
	<total_sales>0</total_sales>
</item>
<item>
	<name><![CDATA[Sustainable cotton basic T-shirt]]></name>
	<short_description></short_description>
	<link>https://salesmanago.store/product/sustainable-cotton-basic-t-shirt-6/</link>
	<price>12</price>
	<currency>USD</currency>
	<image_url>https://salesmanago.store/wp-content/uploads/2021/09/Sustainable-cotton-basic-T-shirt-16.png</image_url>
	<image_url_1>https://salesmanago.store/wp-content/uploads/2021/09/Sustainable-cotton-basic-T-shirt-17.png</image_url_1>
	<sku>107</sku>
	<stock_quantity>17</stock_quantity>
	<categories>Men, T-shirts</categories>
	<tags>Men, T-shirts</tags>
	<total_sales>0</total_sales>
</item>
<item>
	<name><![CDATA[Sustainable cotton basic T-shirt]]></name>
	<short_description></short_description>
	<link>https://salesmanago.store/product/sustainable-cotton-basic-t-shirt-5/</link>
	<price>12</price>
	<currency>USD</currency>
	<image_url>https://salesmanago.store/wp-content/uploads/2021/09/Sustainable-cotton-basic-T-shirt-20.png</image_url>
	<image_url_1>https://salesmanago.store/wp-content/uploads/2021/09/Sustainable-cotton-basic-T-shirt-21.png</image_url_1>
	<sku>108</sku>
	<stock_quantity>14</stock_quantity>
	<categories>Men, T-shirts</categories>
	<tags>Men, T-shirts</tags>
	<total_sales>0</total_sales>
</item>
<item>
	<name><![CDATA[Basic cotton sweater]]></name>
	<short_description></short_description>
	<link>https://salesmanago.store/product/basic-cotton-sweater-4/</link>
	<price>35</price>
	<currency>USD</currency>
	<image_url>https://salesmanago.store/wp-content/uploads/2021/09/Pocket-denim-overshirt-6-1.png</image_url>
	<image_url_1>https://salesmanago.store/wp-content/uploads/2021/09/Pocket-denim-overshirt-7-1.png</image_url_1>
	<sku>109</sku>
	<stock_quantity>12</stock_quantity>
	<categories>Hoodies &amp; Sweatshirts, Men</categories>
	<tags>Hoodies &amp; Sweatshirts, Men, Sweater</tags>
	<total_sales>0</total_sales>
</item>
<item>
	<name><![CDATA[Basic cotton sweater]]></name>
	<short_description></short_description>
	<link>https://salesmanago.store/product/basic-cotton-sweater-3/</link>
	<price>29</price>
	<currency>USD</currency>
	<image_url>https://salesmanago.store/wp-content/uploads/2021/09/Basic-cotton-sweater.png</image_url>
	<image_url_1>https://salesmanago.store/wp-content/uploads/2021/09/Basic-cotton-sweater-1.png</image_url_1>
	<sku>110</sku>
	<stock_quantity>17</stock_quantity>
	<categories>Hoodies &amp; Sweatshirts, Men</categories>
	<tags>Cardigans and sweaters, Men, Sweater</tags>
	<total_sales>0</total_sales>
</item>
<item>
	<name><![CDATA[Basic cotton sweater]]></name>
	<short_description></short_description>
	<link>https://salesmanago.store/product/basic-cotton-sweater-2/</link>
	<price>35</price>
	<currency>USD</currency>
	<image_url>https://salesmanago.store/wp-content/uploads/2021/09/Plush-cotton-sweatshirt-3.png</image_url>
	<image_url_1>https://salesmanago.store/wp-content/uploads/2021/09/Plush-cotton-sweatshirt-4.png</image_url_1>
	<sku>111</sku>
	<stock_quantity>11</stock_quantity>
	<categories>Hoodies &amp; Sweatshirts, Men</categories>
	<tags>Men, Sweater</tags>
	<total_sales>0</total_sales>
</item>
<item>
	<name><![CDATA[Textured knit sweatshirt]]></name>
	<short_description></short_description>
	<link>https://salesmanago.store/product/textured-knit-sweatshirt/</link>
	<price>32</price>
	<currency>USD</currency>
	<image_url>https://salesmanago.store/wp-content/uploads/2021/09/Textured-knit-sweatshirt-2.png</image_url>
	<image_url_1>https://salesmanago.store/wp-content/uploads/2021/09/Textured-knit-sweatshirt.png</image_url_1>
	<sku>112</sku>
	<stock_quantity>11</stock_quantity>
	<categories>Hoodies &amp; Sweatshirts, Men</categories>
	<tags>Men, Sweater</tags>
	<total_sales>0</total_sales>
</item>
<item>
	<name><![CDATA[Hoodie cotton sweatshirt]]></name>
	<short_description></short_description>
	<link>https://salesmanago.store/product/hoodie-cotton-sweatshirt/</link>
	<price>45</price>
	<currency>USD</currency>
	<image_url>https://salesmanago.store/wp-content/uploads/2021/09/Pocket-denim-overshirt-4.png</image_url>
	<image_url_1>https://salesmanago.store/wp-content/uploads/2021/09/Pocket-denim-overshirt-3.png</image_url_1>
	<sku>113</sku>
	<stock_quantity>14</stock_quantity>
	<categories>Hoodies &amp; Sweatshirts, Men</categories>
	<tags>Men, Sweater</tags>
	<total_sales>0</total_sales>
</item>
<item>
	<name><![CDATA[Fine-knit t-shirt with pocket]]></name>
	<short_description></short_description>
	<link>https://salesmanago.store/product/fine-knit-t-shirt-with-pocket-2/</link>
	<price>11</price>
	<currency>USD</currency>
	<image_url>https://salesmanago.store/wp-content/uploads/2021/09/Fine-knit-t-shirt-with-pocket-3.png</image_url>
	<image_url_1>https://salesmanago.store/wp-content/uploads/2021/09/Fine-knit-t-shirt-with-pocket-4.png</image_url_1>
	<sku>114</sku>
	<stock_quantity>7</stock_quantity>
	<categories>Men, T-shirts</categories>
	<tags>Men, T-shirts</tags>
	<total_sales>0</total_sales>
</item>
<item>
	<name><![CDATA[Fine-knit t-shirt with pocket]]></name>
	<short_description></short_description>
	<link>https://salesmanago.store/product/fine-knit-t-shirt-with-pocket/</link>
	<price>11</price>
	<currency>USD</currency>
	<image_url>https://salesmanago.store/wp-content/uploads/2021/09/Fine-knit-t-shirt-with-pocket.png</image_url>
	<image_url_1>https://salesmanago.store/wp-content/uploads/2021/09/Fine-knit-t-shirt-with-pocket-1.png</image_url_1>
	<sku>115</sku>
	<stock_quantity>8</stock_quantity>
	<categories>Men, T-shirts</categories>
	<tags>Men, T-shirts</tags>
	<total_sales>0</total_sales>
</item>
<item>
	<name><![CDATA[Cotton jacket]]></name>
	<short_description></short_description>
	<link>https://salesmanago.store/product/cotton-jacket/</link>
	<price>59</price>
	<currency>USD</currency>
	<image_url>https://salesmanago.store/wp-content/uploads/2021/09/Cotton-jacket-2.png</image_url>
	<image_url_1>https://salesmanago.store/wp-content/uploads/2021/09/Cotton-jacket.png</image_url_1>
	<sku>116</sku>
	<stock_quantity>16</stock_quantity>
	<categories>Jackets &amp; Coats, Men</categories>
	<tags>Jackets, Jackets and Coats, Men</tags>
	<total_sales>0</total_sales>
</item>
<item>
	<name><![CDATA[Zipped high collar cardigan]]></name>
	<short_description></short_description>
	<link>https://salesmanago.store/product/zipped-high-collar-cardigan/</link>
	<price>40</price>
	<currency>USD</currency>
	<image_url>https://salesmanago.store/wp-content/uploads/2021/09/Zipped-high-collar-cardigan-1.png</image_url>
	<image_url_1>https://salesmanago.store/wp-content/uploads/2021/09/Zipped-high-collar-cardigan-2.png</image_url_1>
	<sku>117</sku>
	<stock_quantity>13</stock_quantity>
	<categories>Hoodies &amp; Sweatshirts, Men</categories>
	<tags>Cardigans, Hoodies &amp; Sweatshirts, Men</tags>
	<total_sales>0</total_sales>
</item>
<item>
	<name><![CDATA[Waterproof bomber jacket]]></name>
	<short_description></short_description>
	<link>https://salesmanago.store/product/waterproof-bomber-jacket/</link>
	<price>55</price>
	<currency>USD</currency>
	<image_url>https://salesmanago.store/wp-content/uploads/2021/09/Waterproof-bomber-jacket-3.png</image_url>
	<image_url_1>https://salesmanago.store/wp-content/uploads/2021/09/Waterproof-bomber-jacket-2.png</image_url_1>
	<sku>118</sku>
	<stock_quantity>12</stock_quantity>
	<categories>Jackets &amp; Coats, Men</categories>
	<tags>Jackets, Jackets and Coats, Men</tags>
	<total_sales>0</total_sales>
</item>
<item>
	<name><![CDATA[V-neck sweater]]></name>
	<short_description></short_description>
	<link>https://salesmanago.store/product/v-neck-sweater/</link>
	<price>35</price>
	<currency>USD</currency>
	<image_url>https://salesmanago.store/wp-content/uploads/2021/09/V-neck-sweater-1.png</image_url>
	<image_url_1>https://salesmanago.store/wp-content/uploads/2021/09/V-neck-sweater-2.png</image_url_1>
	<sku>119</sku>
	<stock_quantity>14</stock_quantity>
	<categories>Hoodies &amp; Sweatshirts, Men</categories>
	<tags>Men, Sweater</tags>
	<total_sales>0</total_sales>
</item>
<item>
	<name><![CDATA[Long shirt with a vest]]></name>
	<short_description></short_description>
	<link>https://salesmanago.store/product/long-shirt-with-a-vest/</link>
	<price>45</price>
	<currency>USD</currency>
	<image_url>https://salesmanago.store/wp-content/uploads/2021/09/Long-shirt-with-a-vest.png</image_url>
	<image_url_1>https://salesmanago.store/wp-content/uploads/2021/09/Long-shirt-with-a-vest-1.png</image_url_1>
	<sku>120</sku>
	<stock_quantity>13</stock_quantity>
	<categories>Men, Shirts</categories>
	<tags>Men, Shirts</tags>
	<total_sales>0</total_sales>
</item>
<item>
	<name><![CDATA[100% linen slim fit blazer]]></name>
	<short_description></short_description>
	<link>https://salesmanago.store/product/100-linen-slim-fit-blazer/</link>
	<price>65</price>
	<currency>USD</currency>
	<image_url>https://salesmanago.store/wp-content/uploads/2021/09/100-linen-slim-fit-blazer-3.png</image_url>
	<image_url_1>https://salesmanago.store/wp-content/uploads/2021/09/100-linen-slim-fit-blazer-4.png</image_url_1>
	<sku>121</sku>
	<stock_quantity>15</stock_quantity>
	<categories>Jackets &amp; Coats, Men</categories>
	<tags>Jackets and Coats, Men</tags>
	<total_sales>0</total_sales>
</item>
<item>
	<name><![CDATA[Sustainable cotton basic T-shirt]]></name>
	<short_description></short_description>
	<link>https://salesmanago.store/product/sustainable-cotton-basic-t-shirt-4/</link>
	<price>12</price>
	<currency>USD</currency>
	<image_url>https://salesmanago.store/wp-content/uploads/2021/09/Sustainable-cotton-basic-T-shirt-10.png</image_url>
	<image_url_1>https://salesmanago.store/wp-content/uploads/2021/09/Sustainable-cotton-basic-T-shirt-11.png</image_url_1>
	<sku>122</sku>
	<stock_quantity>15</stock_quantity>
	<categories>Men, T-shirts</categories>
	<tags>Men, T-shirts</tags>
	<total_sales>0</total_sales>
</item>
<item>
	<name><![CDATA[String Market Bag]]></name>
	<short_description></short_description>
	<link>https://salesmanago.store/product/string-market-bag/</link>
	<price>9</price>
	<currency>USD</currency>
	<image_url>https://salesmanago.store/wp-content/uploads/2021/09/String-Market-Bag.png</image_url>
	<sku>123</sku>
	<stock_quantity>13</stock_quantity>
	<categories>Bags</categories>
	<tags>Accessories, Bags</tags>
	<total_sales>0</total_sales>
</item>
<item>
	<name><![CDATA[Regular fit pocket cotton shirt]]></name>
	<short_description></short_description>
	<link>https://salesmanago.store/product/regular-fit-pocket-cotton-shirt/</link>
	<price>35</price>
	<currency>USD</currency>
	<image_url>https://salesmanago.store/wp-content/uploads/2021/09/Regular-fit-pocket-cotton-shirt.png</image_url>
	<image_url_1>https://salesmanago.store/wp-content/uploads/2021/09/Regular-fit-pocket-cotton-shirt-1.png</image_url_1>
	<sku>124</sku>
	<stock_quantity>14</stock_quantity>
	<categories>Men, Shirts</categories>
	<tags>Men, Shirts</tags>
	<total_sales>0</total_sales>
</item>
<item>
	<name><![CDATA[Plush cotton sweatshirt]]></name>
	<short_description></short_description>
	<link>https://salesmanago.store/product/plush-cotton-sweatshirt/</link>
	<price>55</price>
	<currency>USD</currency>
	<image_url>https://salesmanago.store/wp-content/uploads/2021/09/Plush-cotton-sweatshirt-2.png</image_url>
	<image_url_1>https://salesmanago.store/wp-content/uploads/2021/09/Plush-cotton-sweatshirt.png</image_url_1>
	<sku>125</sku>
	<stock_quantity>12</stock_quantity>
	<categories>Hoodies &amp; Sweatshirts, Men</categories>
	<tags>Men, Sweater</tags>
	<total_sales>0</total_sales>
</item>
<item>
	<name><![CDATA[Contrasting knit sweater]]></name>
	<short_description></short_description>
	<link>https://salesmanago.store/product/contrasting-knit-sweater-2/</link>
	<price>30</price>
	<currency>USD</currency>
	<image_url>https://salesmanago.store/wp-content/uploads/2021/09/Contrasting-knit-sweater-4.png</image_url>
	<image_url_1>https://salesmanago.store/wp-content/uploads/2021/09/Contrasting-knit-sweater-3.png</image_url_1>
	<sku>126</sku>
	<stock_quantity>11</stock_quantity>
	<categories>Cardigans and sweaters, Women</categories>
	<tags>Cardigans and sweaters, Sweater, Women</tags>
	<total_sales>0</total_sales>
</item>
<item>
	<name><![CDATA[Satin finish flowy shirt]]></name>
	<short_description></short_description>
	<link>https://salesmanago.store/product/satin-finish-flowy-shirt/</link>
	<price>37</price>
	<currency>USD</currency>
	<image_url>https://salesmanago.store/wp-content/uploads/2021/09/Satin-finish-flowy-shirt-2.png</image_url>
	<image_url_1>https://salesmanago.store/wp-content/uploads/2021/09/Satin-finish-flowy-shirt-1.png</image_url_1>
	<sku>127</sku>
	<stock_quantity>18</stock_quantity>
	<categories>Shirts, Women</categories>
	<tags>Shirts, Women</tags>
	<total_sales>0</total_sales>
</item>
<item>
	<name><![CDATA[Contrasting knit sweater]]></name>
	<short_description></short_description>
	<link>https://salesmanago.store/product/contrasting-knit-sweater/</link>
	<price>30</price>
	<currency>USD</currency>
	<image_url>https://salesmanago.store/wp-content/uploads/2021/09/Contrasting-knit-sweater.png</image_url>
	<image_url_1>https://salesmanago.store/wp-content/uploads/2021/09/Contrasting-knit-sweater-1.png</image_url_1>
	<sku>128</sku>
	<stock_quantity>10</stock_quantity>
	<categories>Cardigans and sweaters, Women</categories>
	<tags>Cardigans and sweaters, Sweater, Women</tags>
	<total_sales>0</total_sales>
</item>
<item>
	<name><![CDATA[Fitted essential suit jacket]]></name>
	<short_description></short_description>
	<link>https://salesmanago.store/product/fitted-essential-suit-jacket/</link>
	<price>55</price>
	<currency>USD</currency>
	<image_url>https://salesmanago.store/wp-content/uploads/2021/09/Fitted-essential-suit-jacket.png</image_url>
	<image_url_1>https://salesmanago.store/wp-content/uploads/2021/09/Fitted-essential-suit-jacket-2.png</image_url_1>
	<sku>129</sku>
	<stock_quantity>8</stock_quantity>
	<categories>Jackets &amp; Coats, Women</categories>
	<tags>Jackets, Jackets and Coats, Women</tags>
	<total_sales>0</total_sales>
</item>
<item>
	<name><![CDATA[Belt handmade coat]]></name>
	<short_description></short_description>
	<link>https://salesmanago.store/product/belt-handmade-coat/</link>
	<price>85</price>
	<currency>USD</currency>
	<image_url>https://salesmanago.store/wp-content/uploads/2021/09/Belt-handmade-coat.png</image_url>
	<image_url_1>https://salesmanago.store/wp-content/uploads/2021/09/Belt-handmade-coat-2.png</image_url_1>
	<sku>130</sku>
	<stock_quantity>11</stock_quantity>
	<categories>Jackets &amp; Coats, Women</categories>
	<tags>Coats, Jackets and Coats, Women</tags>
	<total_sales>0</total_sales>
</item>
<item>
	<name><![CDATA[Hooded knit sweatshirt]]></name>
	<short_description></short_description>
	<link>https://salesmanago.store/product/hooded-knit-sweatshirt/</link>
	<price>35</price>
	<currency>USD</currency>
	<image_url>https://salesmanago.store/wp-content/uploads/2021/09/Hooded-knit-sweatshirt.png</image_url>
	<image_url_1>https://salesmanago.store/wp-content/uploads/2021/09/Hooded-knit-sweatshirt-1.png</image_url_1>
	<sku>131</sku>
	<stock_quantity>14</stock_quantity>
	<categories>Cardigans and sweaters, Women</categories>
	<tags>Sweater, Women</tags>
	<total_sales>0</total_sales>
</item>
<item>
	<name><![CDATA[Knit cotton sweater]]></name>
	<short_description></short_description>
	<link>https://salesmanago.store/product/knit-cotton-sweater/</link>
	<price>22</price>
	<currency>USD</currency>
	<image_url>https://salesmanago.store/wp-content/uploads/2021/09/Knit-cotton-sweater.png</image_url>
	<image_url_1>https://salesmanago.store/wp-content/uploads/2021/09/Knit-cotton-sweater-1.png</image_url_1>
	<sku>132</sku>
	<stock_quantity>16</stock_quantity>
	<categories>Cardigans and sweaters, Women</categories>
	<tags>Cardigans and sweaters, Sweater, Women</tags>
	<total_sales>0</total_sales>
</item>
<item>
	<name><![CDATA[Ultralight button down jacket]]></name>
	<short_description></short_description>
	<link>https://salesmanago.store/product/ultralight-button-down-jacket/</link>
	<price>55</price>
	<currency>USD</currency>
	<image_url>https://salesmanago.store/wp-content/uploads/2021/09/Ultralight-button-down-jacket.png</image_url>
	<image_url_1>https://salesmanago.store/wp-content/uploads/2021/09/Ultralight-button-down-jacket-1.png</image_url_1>
	<sku>133</sku>
	<stock_quantity>11</stock_quantity>
	<categories>Jackets &amp; Coats, Women</categories>
	<tags>Jackets, Jackets and Coats, Women</tags>
	<total_sales>0</total_sales>
</item>
<item>
	<name><![CDATA[Dot midi dress]]></name>
	<short_description></short_description>
	<link>https://salesmanago.store/product/dot-midi-dress/</link>
	<price>25</price>
	<currency>USD</currency>
	<image_url>https://salesmanago.store/wp-content/uploads/2021/09/Dot-midi-dress.png</image_url>
	<image_url_1>https://salesmanago.store/wp-content/uploads/2021/09/Dot-midi-dress-1.png</image_url_1>
	<sku>134</sku>
	<stock_quantity>7</stock_quantity>
	<categories>Dresses, Women</categories>
	<tags>Dresses, Women</tags>
	<total_sales>0</total_sales>
</item>
<item>
	<name><![CDATA[Midi shirt dress]]></name>
	<short_description></short_description>
	<link>https://salesmanago.store/product/midi-shirt-dress/</link>
	<price>25</price>
	<currency>USD</currency>
	<image_url>https://salesmanago.store/wp-content/uploads/2021/09/Midi-shirt-dress.png</image_url>
	<image_url_1>https://salesmanago.store/wp-content/uploads/2021/09/Midi-shirt-dress-1.png</image_url_1>
	<sku>135</sku>
	<stock_quantity>8</stock_quantity>
	<categories>Dresses, Women</categories>
	<tags>Dresses, Women</tags>
	<total_sales>0</total_sales>
</item>
<item>
	<name><![CDATA[Basic cotton sweater]]></name>
	<short_description></short_description>
	<link>https://salesmanago.store/product/basic-cotton-sweater/</link>
	<price>35</price>
	<currency>USD</currency>
	<image_url>https://salesmanago.store/wp-content/uploads/2021/09/Group-78.png</image_url>
	<image_url_1>https://salesmanago.store/wp-content/uploads/2021/09/Group-79.png</image_url_1>
	<sku>136</sku>
	<stock_quantity>12</stock_quantity>
	<categories>Cardigans and sweaters, Women</categories>
	<tags>Cardigans and sweaters, Sweater, Women</tags>
	<total_sales>0</total_sales>
</item>
<item>
	<name><![CDATA[Sustainable cotton basic T-shirt]]></name>
	<short_description></short_description>
	<link>https://salesmanago.store/product/sustainable-cotton-basic-t-shirt-3/</link>
	<price>12</price>
	<currency>USD</currency>
	<image_url>https://salesmanago.store/wp-content/uploads/2021/09/Sustainable-cotton-basic-T-shirt-9.png</image_url>
	<image_url_1>https://salesmanago.store/wp-content/uploads/2021/09/Sustainable-cotton-basic-T-shirt-7.png</image_url_1>
	<sku>137</sku>
	<stock_quantity>18</stock_quantity>
	<categories>T-shirts, Women</categories>
	<tags>T-shirts, Women</tags>
	<total_sales>0</total_sales>
</item>
<item>
	<name><![CDATA[Sustainable cotton basic T-shirt]]></name>
	<short_description></short_description>
	<link>https://salesmanago.store/product/sustainable-cotton-basic-t-shirt-2/</link>
	<price>12</price>
	<currency>USD</currency>
	<image_url>https://salesmanago.store/wp-content/uploads/2021/09/Sustainable-cotton-basic-T-shirt.png</image_url>
	<image_url_1>https://salesmanago.store/wp-content/uploads/2021/09/Sustainable-cotton-basic-T-shirt-1.png</image_url_1>
	<sku>138</sku>
	<stock_quantity>12</stock_quantity>
	<categories>T-shirts, Women</categories>
	<tags>T-shirts, Women</tags>
	<total_sales>0</total_sales>
</item>
<item>
	<name><![CDATA[Sustainable cotton basic T-shirt]]></name>
	<short_description></short_description>
	<link>https://salesmanago.store/product/sustainable-cotton-basic-t-shirt/</link>
	<price>12</price>
	<currency>USD</currency>
	<image_url>https://salesmanago.store/wp-content/uploads/2021/09/Sustainable-cotton-basic-T-shirt-4.png</image_url>
	<image_url_1>https://salesmanago.store/wp-content/uploads/2021/09/Sustainable-cotton-basic-T-shirt-5.png</image_url_1>
	<sku>139</sku>
	<stock_quantity>17</stock_quantity>
	<categories>T-shirts, Women</categories>
	<tags>T-shirts, Women</tags>
	<total_sales>0</total_sales>
</item>
<item>
	<name><![CDATA[Lyocell pleated dress]]></name>
	<short_description></short_description>
	<link>https://salesmanago.store/product/lyocell-pleated-dress/</link>
	<price>42</price>
	<currency>USD</currency>
	<image_url>https://salesmanago.store/wp-content/uploads/2021/09/Lyocell-pleated-dress-2.png</image_url>
	<image_url_1>https://salesmanago.store/wp-content/uploads/2021/09/Lyocell-pleated-dress.png</image_url_1>
	<sku>140</sku>
	<stock_quantity>14</stock_quantity>
	<categories>Dresses, Women</categories>
	<tags>Dresses, Women</tags>
	<total_sales>0</total_sales>
</item>
<item>
	<name><![CDATA[100% cotton sweatshirt]]></name>
	<short_description></short_description>
	<link>https://salesmanago.store/product/100-cotton-sweatshirt/</link>
	<price>32</price>
	<currency>USD</currency>
	<image_url>https://salesmanago.store/wp-content/uploads/2021/09/100-cotton-sweatshirt.png</image_url>
	<image_url_1>https://salesmanago.store/wp-content/uploads/2021/09/100-cotton-sweatshirt-1.png</image_url_1>
	<sku>141</sku>
	<stock_quantity>13</stock_quantity>
	<categories>Cardigans and sweaters, Women</categories>
	<tags>Cardigans and sweaters, Sweater, Women</tags>
	<total_sales>0</total_sales>
</item>
<item>
	<name><![CDATA[Essential cotton-blend shirt]]></name>
	<short_description></short_description>
	<link>https://salesmanago.store/product/essential-cotton-blend-shirt/</link>
	<price>35</price>
	<currency>USD</currency>
	<image_url>https://salesmanago.store/wp-content/uploads/2021/09/Essential-cotton-blend-shirt-1.png</image_url>
	<image_url_1>https://salesmanago.store/wp-content/uploads/2021/09/Essential-cotton-blend-shirt.png</image_url_1>
	<sku>142</sku>
	<stock_quantity>15</stock_quantity>
	<categories>Shirts, Women</categories>
	<tags>Shirts, Women</tags>
	<total_sales>0</total_sales>
</item>
<item>
	<name><![CDATA[Crop skinny trousers]]></name>
	<short_description></short_description>
	<link>https://salesmanago.store/product/crop-skinny-trousers/</link>
	<price>37</price>
	<currency>USD</currency>
	<image_url>https://salesmanago.store/wp-content/uploads/2021/09/Crop-skinny-trousers.png</image_url>
	<sku>143</sku>
	<stock_quantity>14</stock_quantity>
	<categories>Trousers, Women</categories>
	<tags>Trousers, Women</tags>
	<total_sales>0</total_sales>
</item>
<item>
	<name><![CDATA[Striped suit blazer]]></name>
	<short_description></short_description>
	<link>https://salesmanago.store/product/striped-suit-blazer/</link>
	<price>45</price>
	<currency>USD</currency>
	<image_url>https://salesmanago.store/wp-content/uploads/2021/09/Striped-suit-blazer.png</image_url>
	<image_url_1>https://salesmanago.store/wp-content/uploads/2021/09/Striped-suit-blazer-1.png</image_url_1>
	<sku>144</sku>
	<stock_quantity>12</stock_quantity>
	<categories>Jackets &amp; Coats, Women</categories>
	<tags>Jackets and Coats, Women</tags>
	<total_sales>0</total_sales>
</item>
<item>
	<name><![CDATA[Turtleneck knitted sweater]]></name>
	<short_description></short_description>
	<link>https://salesmanago.store/product/turtleneck-knitted-sweater/</link>
	<price>32</price>
	<currency>USD</currency>
	<image_url>https://salesmanago.store/wp-content/uploads/2021/09/Turtleneck-knitted-sweater.png</image_url>
	<image_url_1>https://salesmanago.store/wp-content/uploads/2021/09/Turtleneck-knitted-sweater-1.png</image_url_1>
	<sku>145</sku>
	<stock_quantity>17</stock_quantity>
	<categories>Cardigans and sweaters, Women</categories>
	<tags>Cardigans and sweaters, Sweater, Women</tags>
	<total_sales>0</total_sales>
</item>
<item>
	<name><![CDATA[Oversized sweatshirt with pockets]]></name>
	<short_description></short_description>
	<link>https://salesmanago.store/product/oversized-sweatshirt-with-pockets-2/</link>
	<price>35</price>
	<currency>USD</currency>
	<image_url>https://salesmanago.store/wp-content/uploads/2021/09/Oversized-sweatshirt-with-pockets-3.png</image_url>
	<image_url_1>https://salesmanago.store/wp-content/uploads/2021/09/Oversized-sweatshirt-with-pockets-1.png</image_url_1>
	<sku>146</sku>
	<stock_quantity>13</stock_quantity>
	<categories>Cardigans and sweaters, Women</categories>
	<tags>Cardigans and sweaters, Sweater, Women</tags>
	<total_sales>0</total_sales>
</item>
<item>
	<name><![CDATA[Handmade crochet hat]]></name>
	<short_description></short_description>
	<link>https://salesmanago.store/product/handmade-crochet-hat-2/</link>
	<price>15</price>
	<currency>USD</currency>
	<image_url>https://salesmanago.store/wp-content/uploads/2021/09/Handmade-crochet-hat-3.png</image_url>
	<image_url_1>https://salesmanago.store/wp-content/uploads/2021/09/Handmade-crochet-hat-2.png</image_url_1>
	<sku>147</sku>
	<stock_quantity>15</stock_quantity>
	<categories>Accessories, Summer Hat, Women</categories>
	<tags>Hats, Women</tags>
	<total_sales>0</total_sales>
</item>
<item>
	<name><![CDATA[Cotton classic trench]]></name>
	<short_description></short_description>
	<link>https://salesmanago.store/product/cotton-classic-trench-2/</link>
	<price>65</price>
	<currency>USD</currency>
	<image_url>https://salesmanago.store/wp-content/uploads/2021/09/Cotton-classic-trench-1.png</image_url>
	<image_url_1>https://salesmanago.store/wp-content/uploads/2021/09/Cotton-classic-trench-2.png</image_url_1>
	<sku>148</sku>
	<stock_quantity>14</stock_quantity>
	<categories>Jackets &amp; Coats, Women</categories>
	<tags>Jackets and Coats, Women</tags>
	<total_sales>0</total_sales>
</item>
<item>
	<name><![CDATA[Open neckline body]]></name>
	<short_description></short_description>
	<link>https://salesmanago.store/product/open-neckline-body-2/</link>
	<price>25</price>
	<currency>USD</currency>
	<image_url>https://salesmanago.store/wp-content/uploads/2021/09/Open-neckline-body-1.png</image_url>
	<image_url_1>https://salesmanago.store/wp-content/uploads/2021/09/Open-neckline-body-3.png</image_url_1>
	<sku>149</sku>
	<stock_quantity>12</stock_quantity>
	<categories>Underwear and lingerie Bodies</categories>
	<tags>Bodies, Women</tags>
	<total_sales>0</total_sales>
</item>
<item>
	<name><![CDATA[Knit short cardigan]]></name>
	<short_description></short_description>
	<link>https://salesmanago.store/product/knit-short-cardigan-2/</link>
	<price>35</price>
	<currency>USD</currency>
	<image_url>https://salesmanago.store/wp-content/uploads/2021/09/Knit-short-cardigan-1.png</image_url>
	<image_url_1>https://salesmanago.store/wp-content/uploads/2021/09/Knit-short-cardigan-1-1.png</image_url_1>
	<sku>150</sku>
	<stock_quantity>13</stock_quantity>
	<categories>Cardigans and sweaters, Women</categories>
	<tags>Cardigans, Cardigans and sweaters, Women</tags>
	<total_sales>0</total_sales>
</item>
</root><!-- Product XML Feeds for WooCommerce -->
<!--Created By: https://wpfactory.com/item/product-xml-feeds-woocommerce/ @ 2021-10-07 07:44:05-->
